ez_disk_cache/__init__.py
ez_disk_cache/disk_cache.py
ez_disk_cache-0.0.3.dist-info/METADATA
ez_disk_cache-0.0.3.dist-info/WHEEL
ez_disk_cache-0.0.3.dist-info/licenses/LICENSE
ez_disk_cache-0.0.3.dist-info/RECORD
