Metadata-Version: 2.1
Name: ez-disk-cache
Version: 0.0.3
Summary: A smart decorator to cache function results transparently to disk.
Project-URL: Homepage, https://github.com/robvoe/ez-disk-cache
Project-URL: Bug Tracker, https://github.com/robvoe/ez-disk-cache/issues
Author: Robert Voelckner
License-File: LICENSE
Classifier: License :: OSI Approved :: MIT License
Classifier: Operating System :: OS Independent
Classifier: Programming Language :: Python :: 3
Requires-Python: >=3.8
Requires-Dist: pyyaml>=6.0
